despasito/__init__.py
despasito/__main__.py
despasito/_version.py
despasito/fundamental_constants.py
despasito/main.py
despasito/equations_of_state/__init__.py
despasito/equations_of_state/combining_rule_types.py
despasito/equations_of_state/constants.py
despasito/equations_of_state/eos_toolbox.py
despasito/equations_of_state/interface.py
despasito/equations_of_state/cubic/__init__.py
despasito/equations_of_state/cubic/peng_robinson.py
despasito/equations_of_state/saft/Aassoc.py
despasito/equations_of_state/saft/Aideal.py
despasito/equations_of_state/saft/__init__.py
despasito/equations_of_state/saft/gamma_mie.py
despasito/equations_of_state/saft/gamma_sw.py
despasito/equations_of_state/saft/saft.py
despasito/equations_of_state/saft/saft_toolbox.py
despasito/equations_of_state/saft/saft_variant_example.py
despasito/equations_of_state/saft/compiled_modules/ext_Aassoc_cython.cpython-312-darwin.so
despasito/equations_of_state/saft/compiled_modules/ext_gamma_mie_cython.cpython-312-darwin.so
despasito/input_output/__init__.py
despasito/input_output/read_input.py
despasito/input_output/write_output.py
despasito/parameter_fitting/__init__.py
despasito/parameter_fitting/constraint_types.py
despasito/parameter_fitting/fit_functions.py
despasito/parameter_fitting/global_methods.py
despasito/parameter_fitting/interface.py
despasito/parameter_fitting/data_classes/TLVE.py
despasito/parameter_fitting/data_classes/__init__.py
despasito/parameter_fitting/data_classes/flash.py
despasito/parameter_fitting/data_classes/liquid_density.py
despasito/parameter_fitting/data_classes/saturation_properties.py
despasito/parameter_fitting/data_classes/solubility_parameter.py
despasito/tests/__init__.py
despasito/tests/test_fit_mix.py
despasito/tests/test_fit_pure.py
despasito/tests/test_input_output.py
despasito/tests/test_logging.py
despasito/tests/test_peng_robinson.py
despasito/tests/test_saft_gamma_mie.py
despasito/tests/test_saft_gamma_sw.py
despasito/tests/test_thermo.py
despasito-0.4.1.dist-info/METADATA
despasito-0.4.1.dist-info/WHEEL
despasito-0.4.1.dist-info/top_level.txt
despasito-0.4.1.dist-info/RECORD
