Metadata-Version: 2.2
Name: despasito
Version: 0.4.1
Summary: Determining Equilibrium State and Parametrization Application for SAFT, Intended for Thermodynamic Output
Author: Nathan Duff
Author-email: "Jennifer A. Clark" <jennifer.clark@gnarlyoak.com>
License: BSD-3-Clause
Project-URL: GitHub Source, https://github.com/Santiso-Group/despasito
Project-URL: Documentation, https://despasito.readthedocs.io/en/latest/
Classifier: Programming Language :: Python :: 3
Requires-Python: >=3.8
Requires-Dist: numpy
Requires-Dist: scipy
Requires-Dist: numba
Requires-Dist: flake8
Provides-Extra: test
Requires-Dist: pytest>=6.1.2; extra == "test"
Provides-Extra: docs
Requires-Dist: sphinx; extra == "docs"
Requires-Dist: sphinx_rtd_theme; extra == "docs"
Requires-Dist: sphinx-argparse; extra == "docs"
Requires-Dist: m2r2; extra == "docs"
Requires-Dist: sphinxcontrib-napoleon; extra == "docs"
